TEST/__init__.py
TEST/data.py
pygittesting-0.2.2.dist-info/LICENSE
pygittesting-0.2.2.dist-info/METADATA
pygittesting-0.2.2.dist-info/WHEEL
pygittesting-0.2.2.dist-info/top_level.txt
pygittesting-0.2.2.dist-info/RECORD
