Metadata-Version: 2.1
Name: pygittesting
Version: 0.2.2
Summary: This is a simple package which is used in HackBot Support Pyrogram + Telethon
Home-page: https://github.com/LEGEND-AI/exampl_test
Author: LegendBoy
Author-email: krishna045jaiswal@gmail.com
License: GNU General Public License v3.0
Keywords: test
Classifier: Framework :: AsyncIO
Classifier: Development Status :: 3 - Alpha
Classifier: Intended Audience :: Developers
Classifier: Natural Language :: English
Classifier: Operating System :: OS Independent
Classifier: Programming Language :: Python :: 3.7
Classifier: Programming Language :: Python :: 3.8
Classifier: Programming Language :: Python :: 3.9
Classifier: Programming Language :: Python :: 3.10
Classifier: Topic :: Internet :: WWW/HTTP
Classifier: Topic :: Software Development :: Libraries
Classifier: Topic :: Software Development :: Build Tools
License-File: LICENSE
Requires-Dist: pyrogram
Requires-Dist: telethon
